UnetsMM/__init__.py
UnetsMM/vanilla_multimodelU.py
UnetsMM-0.0.1.dist-info/LICENSE
UnetsMM-0.0.1.dist-info/METADATA
UnetsMM-0.0.1.dist-info/WHEEL
UnetsMM-0.0.1.dist-info/top_level.txt
UnetsMM-0.0.1.dist-info/RECORD
