Metadata-Version: 2.1
Name: UnetsMM
Version: 0.0.1
Summary: module to create architecture of multi modal Unets
Home-page: https://github.com/LorenzoBrochier/Unets.git
Download-URL: 
Author: Lorenzo Brochier
Author-email: 
License: UNKNOWN
Keywords: Deep Learning,Unet
Platform: UNKNOWN
License-File: LICENSE
